gpterm/__init__.py
gpterm/config.py
gpterm/enums.py
gpterm/gpt_terminal.py
gpterm/shell.py
gpterm/utils.py
gpterm-0.2.9.dist-info/LICENSE
gpterm-0.2.9.dist-info/METADATA
gpterm-0.2.9.dist-info/WHEEL
gpterm-0.2.9.dist-info/entry_points.txt
gpterm-0.2.9.dist-info/top_level.txt
gpterm-0.2.9.dist-info/RECORD
