Metadata-Version: 2.1
Name: gpterm
Version: 0.2.9
Summary: A Terminal emulation to interact with OpenAI's GPT models
Home-page: https://github.com/jairus-kope/gpterm
Author: Jairus
Author-email: jairus.kope@gmail.com
Classifier: Programming Language :: Python :: 3
Classifier: License :: OSI Approved :: MIT License
Classifier: Operating System :: MacOS :: MacOS X
Requires-Python: >=3.9.6
License-File: LICENSE
Requires-Dist: openai (>=0.27.2)
Requires-Dist: tiktoken (>=0.3.2)
Requires-Dist: rich (>=13.3.1)
Requires-Dist: pyyaml (>=6.0)
